neverland_pylib/__init__.py
neverland_pylib/compiler/__init__.py
neverland_pylib/compiler/compile.py
neverland_pylib-0.1.dev1.dist-info/LICENSE
neverland_pylib-0.1.dev1.dist-info/METADATA
neverland_pylib-0.1.dev1.dist-info/WHEEL
neverland_pylib-0.1.dev1.dist-info/entry_points.txt
neverland_pylib-0.1.dev1.dist-info/top_level.txt
neverland_pylib-0.1.dev1.dist-info/RECORD
